DRLZ/__init__.py
DRLZ/DDPG/__init__.py
DRLZ/DDPG/actor.py
DRLZ/DDPG/agent.py
DRLZ/DDPG/critic.py
DRLZ/DDPG/ddpg.py
DRLZ/DQN/__init__.py
DRLZ/DQN/agent.py
DRLZ/DQN/dqn.py
DRLZ/MADDPG/__init__.py
DRLZ/MADDPG/maddpg.py
DRLZ/QL/__init__.py
DRLZ/QL/ql.py
DRLZ/utils/__init__.py
DRLZ/utils/buffer.py
DRLZ/utils/env.py
DRLZ/utils/new_env.py
DRLZ/utils/noise.py
DRLZ/utils/tool.py
DRLZ-1.0.0.dist-info/METADATA
DRLZ-1.0.0.dist-info/WHEEL
DRLZ-1.0.0.dist-info/top_level.txt
DRLZ-1.0.0.dist-info/RECORD
